sinapsis_dfine/src/sinapsis_dfine/__init__.py
sinapsis_dfine/src/sinapsis_dfine/helpers/__init__.py
sinapsis_dfine/src/sinapsis_dfine/helpers/dataset_utils.py
sinapsis_dfine/src/sinapsis_dfine/helpers/env_var_keys.py
sinapsis_dfine/src/sinapsis_dfine/helpers/metrics.py
sinapsis_dfine/src/sinapsis_dfine/helpers/schemas.py
sinapsis_dfine/src/sinapsis_dfine/helpers/tags.py
sinapsis_dfine/src/sinapsis_dfine/templates/__init__.py
sinapsis_dfine/src/sinapsis_dfine/templates/dfine_base.py
sinapsis_dfine/src/sinapsis_dfine/templates/dfine_inference.py
sinapsis_dfine/src/sinapsis_dfine/templates/dfine_training.py
sinapsis_object_detection-0.4.1.dist-info/licenses/LICENSE
sinapsis_rfdetr/src/sinapsis_rfdetr/__init__.py
sinapsis_rfdetr/src/sinapsis_rfdetr/helpers/__init__.py
sinapsis_rfdetr/src/sinapsis_rfdetr/helpers/rfdetr_helpers.py
sinapsis_rfdetr/src/sinapsis_rfdetr/helpers/tags.py
sinapsis_rfdetr/src/sinapsis_rfdetr/templates/__init__.py
sinapsis_rfdetr/src/sinapsis_rfdetr/templates/rfdetr_export.py
sinapsis_rfdetr/src/sinapsis_rfdetr/templates/rfdetr_inference.py
sinapsis_rfdetr/src/sinapsis_rfdetr/templates/rfdetr_model_base.py
sinapsis_rfdetr/src/sinapsis_rfdetr/templates/rfdetr_train.py
sinapsis_ultralytics/src/sinapsis_ultralytics/__init__.py
sinapsis_ultralytics/src/sinapsis_ultralytics/helpers/__init__.py
sinapsis_ultralytics/src/sinapsis_ultralytics/helpers/params.py
sinapsis_ultralytics/src/sinapsis_ultralytics/helpers/tags.py
sinapsis_ultralytics/src/sinapsis_ultralytics/helpers/ultralytics_predict_helpers.py
sinapsis_ultralytics/src/sinapsis_ultralytics/templates/__init__.py
sinapsis_ultralytics/src/sinapsis_ultralytics/templates/ultralytics_base.py
sinapsis_ultralytics/src/sinapsis_ultralytics/templates/ultralytics_export.py
sinapsis_ultralytics/src/sinapsis_ultralytics/templates/ultralytics_predict.py
sinapsis_ultralytics/src/sinapsis_ultralytics/templates/ultralytics_train.py
sinapsis_ultralytics/src/sinapsis_ultralytics/templates/ultralytics_val.py
sinapsis_object_detection-0.4.1.dist-info/METADATA
sinapsis_object_detection-0.4.1.dist-info/WHEEL
sinapsis_object_detection-0.4.1.dist-info/top_level.txt
sinapsis_object_detection-0.4.1.dist-info/RECORD
