Metadata-Version: 2.4
Name: sinapsis-object-detection
Version: 0.4.1
Summary: Mono repo with packages for inference and training with object detection models
Author-email: SinapsisAI <dev@sinapsis.tech>
Project-URL: Homepage, https://sinapsis.tech
Project-URL: Documentation, https://docs.sinapsis.tech/docs
Project-URL: Tutorials, https://docs.sinapsis.tech/tutorials
Project-URL: Repository, https://github.com/Sinapsis-AI/sinapsis-object-detection.git
Requires-Python: >=3.10
License-File: LICENSE
Requires-Dist: sinapsis>=0.1.1
Provides-Extra: all
Requires-Dist: sinapsis-dfine[all]; extra == "all"
Requires-Dist: sinapsis-object-detection[gradio-app]; extra == "all"
Requires-Dist: sinapsis-rfdetr[all]; extra == "all"
Requires-Dist: sinapsis-ultralytics[all]; extra == "all"
Provides-Extra: gradio-app
Requires-Dist: sinapsis[webapp]>=0.2.2; extra == "gradio-app"
Dynamic: license-file
